asahi/extras/__init__.py
asahi/extras/__version__.py
asahi_extras-0.2.0.dist-info/LICENSE
asahi_extras-0.2.0.dist-info/WHEEL
asahi_extras-0.2.0.dist-info/METADATA
asahi_extras-0.2.0.dist-info/RECORD
